weekly/__init__.py
weekly/checkers/__init__.py
weekly/checkers/base.py
weekly/checkers/ci_cd.py
weekly/checkers/code_quality.py
weekly/checkers/dependencies.py
weekly/checkers/docs.py
weekly/checkers/style.py
weekly/checkers/testing.py
weekly/cli.py
weekly/core/analyzer.py
weekly/core/project.py
weekly/core/repo_status.py
weekly/core/report.py
weekly/git_analyzer.py
weekly/git_report.py
weekly/git_scanner.py
weekly/py.typed
weekly/reporter.py
weekly-0.1.33.dist-info/LICENSE
weekly-0.1.33.dist-info/METADATA
weekly-0.1.33.dist-info/NOTICE
weekly-0.1.33.dist-info/WHEEL
weekly-0.1.33.dist-info/entry_points.txt
weekly-0.1.33.dist-info/RECORD
