Metadata-Version: 2.3
Name: weekly
Version: 0.1.33
Summary: A comprehensive Python project quality analyzer that provides actionable next steps for improving your project
License: Apache-2.0
Keywords: code quality,analysis,linter,formatter,ci-cd,dependencies,static analysis,code review,best practices
Author: Tom Sapletta
Author-email: info@softreck.dev
Requires-Python: >=3.8.1,<4.0
Classifier: Development Status :: 3 - Alpha
Classifier: Intended Audience :: Developers
Classifier: License :: OSI Approved :: Apache Software License
Classifier: Programming Language :: Python :: 3
Classifier: Programming Language :: Python :: 3.9
Classifier: Programming Language :: Python :: 3.10
Classifier: Programming Language :: Python :: 3.11
Classifier: Programming Language :: Python :: 3.12
Classifier: Programming Language :: Python :: 3.13
Classifier: Programming Language :: Python :: 3.8
Classifier: Topic :: Software Development
Classifier: Topic :: Software Development :: Build Tools
Classifier: Topic :: Software Development :: Quality Assurance
Classifier: Topic :: Software Development :: Testing
Classifier: Topic :: Utilities
Classifier: Typing :: Typed
Requires-Dist: click (>=8.1.3,<9.0.0)
Requires-Dist: python-dotenv (>=1.0.0,<2.0.0)
Requires-Dist: pyyaml (>=6.0.0,<7.0.0)
Requires-Dist: rich (>=13.4.1,<14.0.0)
Requires-Dist: toml (>=0.10.2,<0.11.0)
Requires-Dist: tomli (>=2.0.1,<3.0.0) ; python_version < "3.11"
Project-URL: Bug Tracker, https://github.com/wronai/weekly/issues
Project-URL: Changelog, https://github.com/wronai/weekly/blob/main/CHANGELOG.md
Project-URL: Documentation, https://weekly.readthedocs.io
Project-URL: Discussions, https://github.com/wronai/weekly/discussions
Project-URL: Homepage, https://github.com/wronai/weekly
Project-URL: Repository, https://github.com/wronai/weekly
Project-URL: Source Code, https://github.com/wronai/weekly
